textformatter_plus/__init__.py
textformatter_plus/text_formatter.py
textformatter_plus/validator.py
textformatter_plus-1.0.4.dist-info/METADATA
textformatter_plus-1.0.4.dist-info/WHEEL
textformatter_plus-1.0.4.dist-info/top_level.txt
textformatter_plus-1.0.4.dist-info/RECORD
