Metadata-Version: 2.4
Name: textformatter-plus
Version: 1.0.4
Summary: A powerful Python package for text formatting and validation. Includes utilities for text transformation (title case, snake case, reverse, etc.) and data validation (email, phone, password strength). Perfect for data processing, form validation, and text manipulation tasks.
Home-page: https://github.com/yourusername/textformatter-plus
Author: Your Company Name
Author-email: your.email@example.com
Project-URL: Bug Reports, https://github.com/yourusername/textformatter-plus/issues
Project-URL: Source, https://github.com/yourusername/textformatter-plus
Project-URL: Documentation, https://github.com/yourusername/textformatter-plus#readme
Keywords: text formatting,validation,text processing,utilities,professional,text manipulation
Classifier: Development Status :: 4 - Beta
Classifier: Intended Audience :: Developers
Classifier: License :: OSI Approved :: MIT License
Classifier: Operating System :: OS Independent
Classifier: Programming Language :: Python :: 3
Classifier: Programming Language :: Python :: 3.8
Classifier: Programming Language :: Python :: 3.9
Classifier: Programming Language :: Python :: 3.10
Classifier: Programming Language :: Python :: 3.11
Classifier: Programming Language :: Python :: 3.12
Classifier: Programming Language :: Python :: 3.13
Requires-Python: >=3.8
Dynamic: author
Dynamic: author-email
Dynamic: classifier
Dynamic: description
Dynamic: description-content-type
Dynamic: home-page
Dynamic: keywords
Dynamic: project-url
Dynamic: requires-python
Dynamic: summary
